{
	"openapi": "3.0.0",
	"components": {
		"examples": {},
		"headers": {},
		"parameters": {},
		"requestBodies": {},
		"responses": {},
		"schemas": {
			"CreatedIdResponse": {
				"properties": {
					"id": {
						"type": "number",
						"format": "double"
					},
					"username": {
						"type": "string"
					},
					"email": {
						"type": "string"
					}
				},
				"required": [
					"id",
					"username",
					"email"
				],
				"type": "object",
				"additionalProperties": false
			},
			"ApiResponse_CreatedIdResponse_": {
				"properties": {
					"success": {
						"type": "boolean",
						"enum": [
							true
						],
						"nullable": false
					},
					"message": {
						"type": "string"
					},
					"data": {
						"$ref": "#/components/schemas/CreatedIdResponse"
					}
				},
				"required": [
					"success",
					"message",
					"data"
				],
				"type": "object",
				"additionalProperties": false
			},
			"ApiErrorResponse": {
				"properties": {
					"success": {
						"type": "boolean",
						"enum": [
							false
						],
						"nullable": false
					},
					"message": {
						"type": "string"
					}
				},
				"required": [
					"success",
					"message"
				],
				"type": "object",
				"additionalProperties": false
			},
			"InitStaffBody": {
				"properties": {
					"username": {
						"type": "string",
						"example": "admin"
					},
					"first_name": {
						"type": "string",
						"example": "Tai"
					},
					"last_name": {
						"type": "string",
						"example": "Tran"
					},
					"email": {
						"type": "string",
						"example": "admin@example.com"
					},
					"password": {
						"type": "string",
						"example": "Aa@123456"
					}
				},
				"required": [
					"username",
					"first_name",
					"last_name",
					"email",
					"password"
				],
				"type": "object",
				"additionalProperties": false
			},
			"StaffResponse": {
				"properties": {
					"id": {
						"type": "number",
						"format": "double"
					},
					"username": {
						"type": "string"
					},
					"first_name": {
						"type": "string"
					},
					"last_name": {
						"type": "string"
					},
					"email": {
						"type": "string"
					},
					"phone": {
						"type": "string",
						"nullable": true
					},
					"address": {
						"type": "string",
						"nullable": true
					},
					"avatar": {
						"type": "string",
						"nullable": true
					},
					"status": {
						"type": "string",
						"enum": [
							"active",
							"inactive"
						]
					},
					"created_at": {
						"type": "string",
						"format": "date-time"
					},
					"updated_at": {
						"type": "string",
						"format": "date-time"
					}
				},
				"required": [
					"id",
					"username",
					"first_name",
					"last_name",
					"email",
					"phone",
					"address",
					"avatar",
					"status",
					"created_at",
					"updated_at"
				],
				"type": "object",
				"additionalProperties": false
			},
			"ApiResponse_StaffResponse_": {
				"properties": {
					"success": {
						"type": "boolean",
						"enum": [
							true
						],
						"nullable": false
					},
					"message": {
						"type": "string"
					},
					"data": {
						"$ref": "#/components/schemas/StaffResponse"
					}
				},
				"required": [
					"success",
					"message",
					"data"
				],
				"type": "object",
				"additionalProperties": false
			},
			"ApiMessageResponse": {
				"properties": {
					"success": {
						"type": "boolean",
						"enum": [
							true
						],
						"nullable": false
					},
					"message": {
						"type": "string"
					}
				},
				"required": [
					"success",
					"message"
				],
				"type": "object",
				"additionalProperties": false
			},
			"StaffUpdateProfileBody": {
				"properties": {
					"first_name": {
						"type": "string",
						"example": "Tai"
					},
					"last_name": {
						"type": "string",
						"example": "Tran"
					},
					"email": {
						"type": "string",
						"example": "admin@example.com"
					},
					"phone": {
						"type": "string",
						"example": "0778946513"
					},
					"address": {
						"type": "string",
						"example": "51 Duong A, TPHCM"
					},
					"avatar": {
						"type": "string",
						"example": "https://example.com/avatar.png"
					}
				},
				"type": "object",
				"additionalProperties": false
			},
			"PaginationMeta": {
				"properties": {
					"total": {
						"type": "number",
						"format": "double"
					},
					"page": {
						"type": "number",
						"format": "double"
					},
					"limit": {
						"type": "number",
						"format": "double"
					},
					"totalPages": {
						"type": "number",
						"format": "double"
					}
				},
				"required": [
					"total",
					"page",
					"limit",
					"totalPages"
				],
				"type": "object",
				"additionalProperties": false
			},
			"StaffListResponse": {
				"properties": {
					"staff": {
						"items": {
							"$ref": "#/components/schemas/StaffResponse"
						},
						"type": "array"
					},
					"pagination": {
						"$ref": "#/components/schemas/PaginationMeta"
					}
				},
				"required": [
					"staff",
					"pagination"
				],
				"type": "object",
				"additionalProperties": false
			},
			"ApiResponse_StaffListResponse_": {
				"properties": {
					"success": {
						"type": "boolean",
						"enum": [
							true
						],
						"nullable": false
					},
					"message": {
						"type": "string"
					},
					"data": {
						"$ref": "#/components/schemas/StaffListResponse"
					}
				},
				"required": [
					"success",
					"message",
					"data"
				],
				"type": "object",
				"additionalProperties": false
			},
			"CreateStaffBody": {
				"properties": {
					"username": {
						"type": "string",
						"example": "staff01"
					},
					"first_name": {
						"type": "string",
						"example": "Tai"
					},
					"last_name": {
						"type": "string",
						"example": "Tran"
					},
					"email": {
						"type": "string",
						"example": "staff01@example.com"
					},
					"password": {
						"type": "string",
						"example": "Aa@123456"
					}
				},
				"required": [
					"username",
					"first_name",
					"last_name",
					"email",
					"password"
				],
				"type": "object",
				"additionalProperties": false
			},
			"StaffChangePasswordBody": {
				"properties": {
					"oldPassword": {
						"type": "string",
						"example": "Aa@123456"
					},
					"newPassword": {
						"type": "string",
						"example": "Aa@1234567"
					}
				},
				"required": [
					"oldPassword",
					"newPassword"
				],
				"type": "object",
				"additionalProperties": false
			},
			"StaffResetPasswordBody": {
				"properties": {
					"newPassword": {
						"type": "string",
						"example": "Aa@123456"
					}
				},
				"required": [
					"newPassword"
				],
				"type": "object",
				"additionalProperties": false
			},
			"StaffUpdateStatusBody": {
				"properties": {
					"status": {
						"type": "string",
						"enum": [
							"active",
							"inactive"
						],
						"example": "inactive"
					}
				},
				"required": [
					"status"
				],
				"type": "object",
				"additionalProperties": false
			},
			"ProductResponse": {
				"properties": {
					"id": {
						"type": "number",
						"format": "double"
					},
					"name": {
						"type": "string"
					},
					"description": {
						"type": "string",
						"nullable": true
					},
					"price": {
						"type": "number",
						"format": "double"
					},
					"image_url": {
						"type": "string",
						"nullable": true
					},
					"status": {
						"type": "string",
						"enum": [
							"active",
							"inactive"
						]
					},
					"category": {
						"properties": {
							"name": {
								"type": "string"
							},
							"id": {
								"type": "number",
								"format": "double"
							}
						},
						"required": [
							"name",
							"id"
						],
						"type": "object",
						"nullable": true
					},
					"created_at": {
						"type": "string",
						"format": "date-time"
					},
					"updated_at": {
						"type": "string",
						"format": "date-time"
					}
				},
				"required": [
					"id",
					"name",
					"description",
					"price",
					"image_url",
					"status",
					"category",
					"created_at",
					"updated_at"
				],
				"type": "object",
				"additionalProperties": false
			},
			"ProductListResponse": {
				"properties": {
					"products": {
						"items": {
							"$ref": "#/components/schemas/ProductResponse"
						},
						"type": "array"
					},
					"pagination": {
						"$ref": "#/components/schemas/PaginationMeta"
					}
				},
				"required": [
					"products",
					"pagination"
				],
				"type": "object",
				"additionalProperties": false
			},
			"ApiResponse_ProductListResponse_": {
				"properties": {
					"success": {
						"type": "boolean",
						"enum": [
							true
						],
						"nullable": false
					},
					"message": {
						"type": "string"
					},
					"data": {
						"$ref": "#/components/schemas/ProductListResponse"
					}
				},
				"required": [
					"success",
					"message",
					"data"
				],
				"type": "object",
				"additionalProperties": false
			},
			"ApiResponse_ProductResponse-Array_": {
				"properties": {
					"success": {
						"type": "boolean",
						"enum": [
							true
						],
						"nullable": false
					},
					"message": {
						"type": "string"
					},
					"data": {
						"items": {
							"$ref": "#/components/schemas/ProductResponse"
						},
						"type": "array"
					}
				},
				"required": [
					"success",
					"message",
					"data"
				],
				"type": "object",
				"additionalProperties": false
			},
			"ApiResponse_ProductResponse_": {
				"properties": {
					"success": {
						"type": "boolean",
						"enum": [
							true
						],
						"nullable": false
					},
					"message": {
						"type": "string"
					},
					"data": {
						"$ref": "#/components/schemas/ProductResponse"
					}
				},
				"required": [
					"success",
					"message",
					"data"
				],
				"type": "object",
				"additionalProperties": false
			},
			"CreatedProductResponse": {
				"properties": {
					"productId": {
						"type": "number",
						"format": "double"
					},
					"name": {
						"type": "string"
					}
				},
				"required": [
					"productId",
					"name"
				],
				"type": "object",
				"additionalProperties": false
			},
			"ApiResponse_CreatedProductResponse_": {
				"properties": {
					"success": {
						"type": "boolean",
						"enum": [
							true
						],
						"nullable": false
					},
					"message": {
						"type": "string"
					},
					"data": {
						"$ref": "#/components/schemas/CreatedProductResponse"
					}
				},
				"required": [
					"success",
					"message",
					"data"
				],
				"type": "object",
				"additionalProperties": false
			},
			"CreateProductBody": {
				"properties": {
					"category_id": {
						"type": "number",
						"format": "double",
						"example": 1
					},
					"name": {
						"type": "string",
						"example": "iPhone 15"
					},
					"description": {
						"type": "string",
						"example": "Latest Apple smartphone"
					},
					"price": {
						"type": "number",
						"format": "double",
						"example": 999.99
					},
					"image_url": {
						"type": "string",
						"example": "https://example.com/iphone.png"
					}
				},
				"required": [
					"name",
					"price"
				],
				"type": "object",
				"additionalProperties": false
			},
			"UpdateProductBody": {
				"properties": {
					"category_id": {
						"type": "number",
						"format": "double",
						"example": 2
					},
					"name": {
						"type": "string",
						"example": "iPhone 15 Pro"
					},
					"description": {
						"type": "string",
						"example": "Updated description"
					},
					"price": {
						"type": "number",
						"format": "double",
						"example": 1199.99
					},
					"image_url": {
						"type": "string",
						"example": "https://example.com/new.png"
					},
					"status": {
						"type": "string",
						"enum": [
							"active",
							"inactive"
						],
						"example": "active"
					}
				},
				"type": "object",
				"additionalProperties": false
			},
			"OrderResponse": {
				"properties": {
					"id": {
						"type": "number",
						"format": "double"
					},
					"customer_id": {
						"type": "number",
						"format": "double"
					},
					"total_amount": {
						"type": "number",
						"format": "double"
					},
					"status": {
						"type": "string"
					},
					"shipping_address": {
						"type": "string",
						"nullable": true
					},
					"created_at": {
						"type": "string",
						"format": "date-time"
					},
					"updated_at": {
						"type": "string",
						"format": "date-time"
					}
				},
				"required": [
					"id",
					"customer_id",
					"total_amount",
					"status",
					"shipping_address",
					"created_at",
					"updated_at"
				],
				"type": "object",
				"additionalProperties": false
			},
			"OrderListResponse": {
				"properties": {
					"orders": {
						"items": {
							"$ref": "#/components/schemas/OrderResponse"
						},
						"type": "array"
					},
					"pagination": {
						"$ref": "#/components/schemas/PaginationMeta"
					}
				},
				"required": [
					"orders",
					"pagination"
				],
				"type": "object",
				"additionalProperties": false
			},
			"ApiResponse_OrderListResponse_": {
				"properties": {
					"success": {
						"type": "boolean",
						"enum": [
							true
						],
						"nullable": false
					},
					"message": {
						"type": "string"
					},
					"data": {
						"$ref": "#/components/schemas/OrderListResponse"
					}
				},
				"required": [
					"success",
					"message",
					"data"
				],
				"type": "object",
				"additionalProperties": false
			},
			"OrderItemResponse": {
				"properties": {
					"id": {
						"type": "number",
						"format": "double"
					},
					"product_id": {
						"type": "number",
						"format": "double"
					},
					"product_name": {
						"type": "string"
					},
					"product_image": {
						"type": "string",
						"nullable": true
					},
					"quantity": {
						"type": "number",
						"format": "double"
					},
					"price": {
						"type": "number",
						"format": "double"
					}
				},
				"required": [
					"id",
					"product_id",
					"product_name",
					"product_image",
					"quantity",
					"price"
				],
				"type": "object",
				"additionalProperties": false
			},
			"OrderDetailResponse": {
				"properties": {
					"id": {
						"type": "number",
						"format": "double"
					},
					"customer_id": {
						"type": "number",
						"format": "double"
					},
					"total_amount": {
						"type": "number",
						"format": "double"
					},
					"status": {
						"type": "string"
					},
					"shipping_address": {
						"type": "string",
						"nullable": true
					},
					"created_at": {
						"type": "string",
						"format": "date-time"
					},
					"updated_at": {
						"type": "string",
						"format": "date-time"
					},
					"items": {
						"items": {
							"$ref": "#/components/schemas/OrderItemResponse"
						},
						"type": "array"
					}
				},
				"required": [
					"id",
					"customer_id",
					"total_amount",
					"status",
					"shipping_address",
					"created_at",
					"updated_at",
					"items"
				],
				"type": "object",
				"additionalProperties": false
			},
			"ApiResponse_OrderDetailResponse_": {
				"properties": {
					"success": {
						"type": "boolean",
						"enum": [
							true
						],
						"nullable": false
					},
					"message": {
						"type": "string"
					},
					"data": {
						"$ref": "#/components/schemas/OrderDetailResponse"
					}
				},
				"required": [
					"success",
					"message",
					"data"
				],
				"type": "object",
				"additionalProperties": false
			},
			"CreatedOrderResponse": {
				"properties": {
					"id": {
						"type": "number",
						"format": "double"
					},
					"total_amount": {
						"type": "number",
						"format": "double"
					},
					"status": {
						"type": "string"
					}
				},
				"required": [
					"id",
					"total_amount",
					"status"
				],
				"type": "object",
				"additionalProperties": false
			},
			"ApiResponse_CreatedOrderResponse_": {
				"properties": {
					"success": {
						"type": "boolean",
						"enum": [
							true
						],
						"nullable": false
					},
					"message": {
						"type": "string"
					},
					"data": {
						"$ref": "#/components/schemas/CreatedOrderResponse"
					}
				},
				"required": [
					"success",
					"message",
					"data"
				],
				"type": "object",
				"additionalProperties": false
			},
			"CreateOrderItemBody": {
				"properties": {
					"product_id": {
						"type": "number",
						"format": "double",
						"example": 1
					},
					"quantity": {
						"type": "number",
						"format": "double",
						"example": 2
					}
				},
				"required": [
					"product_id",
					"quantity"
				],
				"type": "object",
				"additionalProperties": false
			},
			"CreateOrderBody": {
				"properties": {
					"customer_id": {
						"type": "number",
						"format": "double",
						"example": 1
					},
					"shipping_address": {
						"type": "string",
						"example": "123 Nguyen Trai, Q1, Ho Chi Minh City"
					},
					"items": {
						"items": {
							"$ref": "#/components/schemas/CreateOrderItemBody"
						},
						"type": "array",
						"example": [
							{
								"product_id": 1,
								"quantity": 2
							}
						]
					}
				},
				"required": [
					"customer_id",
					"shipping_address",
					"items"
				],
				"type": "object",
				"additionalProperties": false
			},
			"UpdateOrderStatusBody": {
				"properties": {
					"status": {
						"type": "string",
						"enum": [
							"PENDING",
							"CONFIRMED",
							"SHIPPING",
							"COMPLETED",
							"CANCELLED"
						],
						"example": "CONFIRMED"
					},
					"note": {
						"type": "string",
						"example": "Order confirmed by admin"
					}
				},
				"required": [
					"status"
				],
				"type": "object",
				"additionalProperties": false
			},
			"CancelOrderBody": {
				"properties": {
					"note": {
						"type": "string",
						"example": "Customer requested cancellation"
					}
				},
				"type": "object",
				"additionalProperties": false
			},
			"CustomerResponse": {
				"properties": {
					"id": {
						"type": "number",
						"format": "double"
					},
					"username": {
						"type": "string"
					},
					"first_name": {
						"type": "string"
					},
					"last_name": {
						"type": "string"
					},
					"email": {
						"type": "string"
					},
					"phone": {
						"type": "string",
						"nullable": true
					},
					"address": {
						"type": "string",
						"nullable": true
					},
					"avatar": {
						"type": "string",
						"nullable": true
					},
					"status": {
						"type": "string",
						"enum": [
							"active",
							"inactive"
						]
					},
					"created_at": {
						"type": "string",
						"format": "date-time"
					},
					"updated_at": {
						"type": "string",
						"format": "date-time"
					}
				},
				"required": [
					"id",
					"username",
					"first_name",
					"last_name",
					"email",
					"phone",
					"address",
					"avatar",
					"status",
					"created_at",
					"updated_at"
				],
				"type": "object",
				"additionalProperties": false
			},
			"ApiResponse_CustomerResponse_": {
				"properties": {
					"success": {
						"type": "boolean",
						"enum": [
							true
						],
						"nullable": false
					},
					"message": {
						"type": "string"
					},
					"data": {
						"$ref": "#/components/schemas/CustomerResponse"
					}
				},
				"required": [
					"success",
					"message",
					"data"
				],
				"type": "object",
				"additionalProperties": false
			},
			"ClientUpdateProfileBody": {
				"properties": {
					"first_name": {
						"type": "string",
						"example": "Tran"
					},
					"last_name": {
						"type": "string",
						"example": "Tai"
					},
					"email": {
						"type": "string",
						"example": "newemail@example.com"
					},
					"phone": {
						"type": "string",
						"example": "0901234567"
					},
					"address": {
						"type": "string",
						"example": "123 Le Loi, Q1, TPHCM"
					},
					"avatar": {
						"type": "string",
						"example": "https://example.com/avatar.png"
					}
				},
				"type": "object",
				"additionalProperties": false
			},
			"ClientChangePasswordBody": {
				"properties": {
					"current_password": {
						"type": "string",
						"example": "OldPass@123"
					},
					"new_password": {
						"type": "string",
						"example": "NewPass@456"
					}
				},
				"required": [
					"current_password",
					"new_password"
				],
				"type": "object",
				"additionalProperties": false
			},
			"CustomerListResponse": {
				"properties": {
					"customers": {
						"items": {
							"$ref": "#/components/schemas/CustomerResponse"
						},
						"type": "array"
					},
					"pagination": {
						"$ref": "#/components/schemas/PaginationMeta"
					}
				},
				"required": [
					"customers",
					"pagination"
				],
				"type": "object",
				"additionalProperties": false
			},
			"ApiResponse_CustomerListResponse_": {
				"properties": {
					"success": {
						"type": "boolean",
						"enum": [
							true
						],
						"nullable": false
					},
					"message": {
						"type": "string"
					},
					"data": {
						"$ref": "#/components/schemas/CustomerListResponse"
					}
				},
				"required": [
					"success",
					"message",
					"data"
				],
				"type": "object",
				"additionalProperties": false
			},
			"CreateCustomerBody": {
				"properties": {
					"username": {
						"type": "string",
						"example": "user1"
					},
					"first_name": {
						"type": "string",
						"example": "Tran"
					},
					"last_name": {
						"type": "string",
						"example": "Tai"
					},
					"email": {
						"type": "string",
						"example": "user1@example.com"
					},
					"password": {
						"type": "string",
						"example": "Aa@123456"
					}
				},
				"required": [
					"username",
					"first_name",
					"last_name",
					"email",
					"password"
				],
				"type": "object",
				"additionalProperties": false
			},
			"UpdateCustomerBody": {
				"properties": {
					"first_name": {
						"type": "string",
						"example": "Tran"
					},
					"last_name": {
						"type": "string",
						"example": "Tai"
					},
					"email": {
						"type": "string",
						"example": "user1@example.com"
					},
					"phone": {
						"type": "string",
						"example": "0778946513"
					},
					"address": {
						"type": "string",
						"example": "51 Duong A, TPHCM"
					},
					"avatar": {
						"type": "string",
						"example": "https://example.com/avatar.png"
					}
				},
				"type": "object",
				"additionalProperties": false
			},
			"UpdateCustomerStatusBody": {
				"properties": {
					"status": {
						"type": "string",
						"enum": [
							"active",
							"inactive"
						],
						"example": "inactive"
					}
				},
				"required": [
					"status"
				],
				"type": "object",
				"additionalProperties": false
			},
			"AdminResetPasswordBody": {
				"properties": {
					"new_password": {
						"type": "string",
						"example": "NewPass@123"
					}
				},
				"required": [
					"new_password"
				],
				"type": "object",
				"additionalProperties": false
			},
			"CategoryResponse": {
				"properties": {
					"id": {
						"type": "number",
						"format": "double"
					},
					"name": {
						"type": "string"
					},
					"description": {
						"type": "string",
						"nullable": true
					},
					"status": {
						"type": "string",
						"enum": [
							"active",
							"inactive"
						]
					},
					"created_at": {
						"type": "string",
						"format": "date-time"
					},
					"updated_at": {
						"type": "string",
						"format": "date-time"
					}
				},
				"required": [
					"id",
					"name",
					"description",
					"status",
					"created_at",
					"updated_at"
				],
				"type": "object",
				"additionalProperties": false
			},
			"CategoryListResponse": {
				"properties": {
					"categories": {
						"items": {
							"$ref": "#/components/schemas/CategoryResponse"
						},
						"type": "array"
					},
					"pagination": {
						"$ref": "#/components/schemas/PaginationMeta"
					}
				},
				"required": [
					"categories",
					"pagination"
				],
				"type": "object",
				"additionalProperties": false
			},
			"ApiResponse_CategoryListResponse_": {
				"properties": {
					"success": {
						"type": "boolean",
						"enum": [
							true
						],
						"nullable": false
					},
					"message": {
						"type": "string"
					},
					"data": {
						"$ref": "#/components/schemas/CategoryListResponse"
					}
				},
				"required": [
					"success",
					"message",
					"data"
				],
				"type": "object",
				"additionalProperties": false
			},
			"ApiResponse_CategoryResponse_": {
				"properties": {
					"success": {
						"type": "boolean",
						"enum": [
							true
						],
						"nullable": false
					},
					"message": {
						"type": "string"
					},
					"data": {
						"$ref": "#/components/schemas/CategoryResponse"
					}
				},
				"required": [
					"success",
					"message",
					"data"
				],
				"type": "object",
				"additionalProperties": false
			},
			"CreatedCategoryResponse": {
				"properties": {
					"categoryId": {
						"type": "number",
						"format": "double"
					},
					"name": {
						"type": "string"
					}
				},
				"required": [
					"categoryId",
					"name"
				],
				"type": "object",
				"additionalProperties": false
			},
			"ApiResponse_CreatedCategoryResponse_": {
				"properties": {
					"success": {
						"type": "boolean",
						"enum": [
							true
						],
						"nullable": false
					},
					"message": {
						"type": "string"
					},
					"data": {
						"$ref": "#/components/schemas/CreatedCategoryResponse"
					}
				},
				"required": [
					"success",
					"message",
					"data"
				],
				"type": "object",
				"additionalProperties": false
			},
			"CreateCategoryBody": {
				"properties": {
					"name": {
						"type": "string",
						"example": "Apple"
					},
					"description": {
						"type": "string",
						"example": "Apple test"
					}
				},
				"required": [
					"name"
				],
				"type": "object",
				"additionalProperties": false
			},
			"UpdateCategoryBody": {
				"properties": {
					"name": {
						"type": "string",
						"example": "Apple Updated"
					},
					"description": {
						"type": "string",
						"example": "Apple test updated"
					},
					"status": {
						"type": "string",
						"enum": [
							"active",
							"inactive"
						],
						"example": "active"
					}
				},
				"type": "object",
				"additionalProperties": false
			},
			"StaffLoginResponse": {
				"properties": {
					"token": {
						"type": "string"
					},
					"staff": {
						"$ref": "#/components/schemas/StaffResponse"
					}
				},
				"required": [
					"token",
					"staff"
				],
				"type": "object",
				"additionalProperties": false
			},
			"ApiResponse_StaffLoginResponse_": {
				"properties": {
					"success": {
						"type": "boolean",
						"enum": [
							true
						],
						"nullable": false
					},
					"message": {
						"type": "string"
					},
					"data": {
						"$ref": "#/components/schemas/StaffLoginResponse"
					}
				},
				"required": [
					"success",
					"message",
					"data"
				],
				"type": "object",
				"additionalProperties": false
			},
			"LoginBody": {
				"properties": {
					"username": {
						"type": "string",
						"example": "admin"
					},
					"password": {
						"type": "string",
						"example": "Aa@123456"
					}
				},
				"required": [
					"username",
					"password"
				],
				"type": "object",
				"additionalProperties": false
			},
			"CustomerLoginResponse": {
				"properties": {
					"token": {
						"type": "string"
					},
					"customer": {
						"$ref": "#/components/schemas/CustomerResponse"
					}
				},
				"required": [
					"token",
					"customer"
				],
				"type": "object",
				"additionalProperties": false
			},
			"ApiResponse_CustomerLoginResponse_": {
				"properties": {
					"success": {
						"type": "boolean",
						"enum": [
							true
						],
						"nullable": false
					},
					"message": {
						"type": "string"
					},
					"data": {
						"$ref": "#/components/schemas/CustomerLoginResponse"
					}
				},
				"required": [
					"success",
					"message",
					"data"
				],
				"type": "object",
				"additionalProperties": false
			}
		},
		"securitySchemes": {
			"bearerAuth": {
				"type": "http",
				"scheme": "bearer",
				"bearerFormat": "JWT"
			}
		}
	},
	"info": {
		"title": "BMD Training API",
		"version": "1.0.0",
		"description": "API documentation for BMD Training backend",
		"license": {
			"name": "ISC"
		},
		"contact": {}
	},
	"paths": {
		"/api/admin/staff/init-staff": {
			"post": {
				"operationId": "InitStaff",
				"responses": {
					"200": {
						"description": "Ok",
						"content": {
							"application/json": {
								"schema": {
									"anyOf": [
										{
											"$ref": "#/components/schemas/ApiResponse_CreatedIdResponse_"
										},
										{
											"$ref": "#/components/schemas/ApiErrorResponse"
										}
									]
								}
							}
						}
					}
				},
				"summary": "Initialize the first staff account",
				"tags": [
					"Admin - Staff"
				],
				"security": [],
				"parameters": [
					{
						"in": "header",
						"name": "x-init-secret",
						"required": true,
						"schema": {
							"type": "string"
						}
					}
				],
				"requestBody": {
					"required": true,
					"content": {
						"application/json": {
							"schema": {
								"$ref": "#/components/schemas/InitStaffBody"
							}
						}
					}
				}
			}
		},
		"/api/admin/staff/profile": {
			"get": {
				"operationId": "GetProfile",
				"responses": {
					"200": {
						"description": "Ok",
						"content": {
							"application/json": {
								"schema": {
									"anyOf": [
										{
											"$ref": "#/components/schemas/ApiResponse_StaffResponse_"
										},
										{
											"$ref": "#/components/schemas/ApiErrorResponse"
										}
									]
								}
							}
						}
					}
				},
				"summary": "Get authenticated staff profile",
				"tags": [
					"Admin - Staff"
				],
				"security": [
					{
						"bearerAuth": []
					}
				],
				"parameters": []
			},
			"put": {
				"operationId": "UpdateProfile",
				"responses": {
					"200": {
						"description": "Ok",
						"content": {
							"application/json": {
								"schema": {
									"anyOf": [
										{
											"$ref": "#/components/schemas/ApiMessageResponse"
										},
										{
											"$ref": "#/components/schemas/ApiErrorResponse"
										}
									]
								}
							}
						}
					}
				},
				"summary": "Update authenticated staff profile",
				"tags": [
					"Admin - Staff"
				],
				"security": [
					{
						"bearerAuth": []
					}
				],
				"parameters": [],
				"requestBody": {
					"required": true,
					"content": {
						"application/json": {
							"schema": {
								"$ref": "#/components/schemas/StaffUpdateProfileBody"
							}
						}
					}
				}
			}
		},
		"/api/admin/staff": {
			"get": {
				"operationId": "GetAllStaffProfile",
				"responses": {
					"200": {
						"description": "Ok",
						"content": {
							"application/json": {
								"schema": {
									"anyOf": [
										{
											"$ref": "#/components/schemas/ApiResponse_StaffListResponse_"
										},
										{
											"$ref": "#/components/schemas/ApiErrorResponse"
										}
									]
								}
							}
						}
					}
				},
				"summary": "Get all staff profiles",
				"tags": [
					"Admin - Staff"
				],
				"security": [
					{
						"bearerAuth": []
					}
				],
				"parameters": [
					{
						"in": "query",
						"name": "page",
						"required": false,
						"schema": {
							"default": 1,
							"format": "double",
							"type": "number"
						}
					},
					{
						"in": "query",
						"name": "limit",
						"required": false,
						"schema": {
							"default": 20,
							"format": "double",
							"type": "number"
						}
					}
				]
			},
			"post": {
				"operationId": "CreateStaff",
				"responses": {
					"200": {
						"description": "Ok",
						"content": {
							"application/json": {
								"schema": {
									"anyOf": [
										{
											"$ref": "#/components/schemas/ApiResponse_CreatedIdResponse_"
										},
										{
											"$ref": "#/components/schemas/ApiErrorResponse"
										}
									]
								}
							}
						}
					}
				},
				"summary": "Create a new staff account",
				"tags": [
					"Admin - Staff"
				],
				"security": [
					{
						"bearerAuth": []
					}
				],
				"parameters": [],
				"requestBody": {
					"required": true,
					"content": {
						"application/json": {
							"schema": {
								"$ref": "#/components/schemas/CreateStaffBody"
							}
						}
					}
				}
			}
		},
		"/api/admin/staff/{staffId}": {
			"get": {
				"operationId": "GetStaffById",
				"responses": {
					"200": {
						"description": "Ok",
						"content": {
							"application/json": {
								"schema": {
									"anyOf": [
										{
											"$ref": "#/components/schemas/ApiResponse_StaffResponse_"
										},
										{
											"$ref": "#/components/schemas/ApiErrorResponse"
										}
									]
								}
							}
						}
					}
				},
				"summary": "Get a staff member by ID",
				"tags": [
					"Admin - Staff"
				],
				"security": [
					{
						"bearerAuth": []
					}
				],
				"parameters": [
					{
						"in": "path",
						"name": "staffId",
						"required": true,
						"schema": {
							"format": "double",
							"type": "number"
						}
					}
				]
			}
		},
		"/api/admin/staff/profile/change-password": {
			"put": {
				"operationId": "ChangePassword",
				"responses": {
					"200": {
						"description": "Ok",
						"content": {
							"application/json": {
								"schema": {
									"anyOf": [
										{
											"$ref": "#/components/schemas/ApiMessageResponse"
										},
										{
											"$ref": "#/components/schemas/ApiErrorResponse"
										}
									]
								}
							}
						}
					}
				},
				"summary": "Change password for authenticated staff",
				"tags": [
					"Admin - Staff"
				],
				"security": [
					{
						"bearerAuth": []
					}
				],
				"parameters": [],
				"requestBody": {
					"required": true,
					"content": {
						"application/json": {
							"schema": {
								"$ref": "#/components/schemas/StaffChangePasswordBody"
							}
						}
					}
				}
			}
		},
		"/api/admin/staff/reset-password": {
			"put": {
				"operationId": "ResetPassword",
				"responses": {
					"200": {
						"description": "Ok",
						"content": {
							"application/json": {
								"schema": {
									"anyOf": [
										{
											"$ref": "#/components/schemas/ApiMessageResponse"
										},
										{
											"$ref": "#/components/schemas/ApiErrorResponse"
										}
									]
								}
							}
						}
					}
				},
				"summary": "Reset password for a staff member by ID",
				"tags": [
					"Admin - Staff"
				],
				"security": [
					{
						"bearerAuth": []
					}
				],
				"parameters": [
					{
						"in": "query",
						"name": "id",
						"required": true,
						"schema": {
							"format": "double",
							"type": "number"
						}
					}
				],
				"requestBody": {
					"required": true,
					"content": {
						"application/json": {
							"schema": {
								"$ref": "#/components/schemas/StaffResetPasswordBody"
							}
						}
					}
				}
			}
		},
		"/api/admin/staff/status": {
			"put": {
				"operationId": "UpdateStatus",
				"responses": {
					"200": {
						"description": "Ok",
						"content": {
							"application/json": {
								"schema": {
									"anyOf": [
										{
											"$ref": "#/components/schemas/ApiMessageResponse"
										},
										{
											"$ref": "#/components/schemas/ApiErrorResponse"
										}
									]
								}
							}
						}
					}
				},
				"summary": "Update status of a staff member by ID",
				"tags": [
					"Admin - Staff"
				],
				"security": [
					{
						"bearerAuth": []
					}
				],
				"parameters": [
					{
						"in": "query",
						"name": "id",
						"required": true,
						"schema": {
							"format": "double",
							"type": "number"
						}
					}
				],
				"requestBody": {
					"required": true,
					"content": {
						"application/json": {
							"schema": {
								"$ref": "#/components/schemas/StaffUpdateStatusBody"
							}
						}
					}
				}
			}
		},
		"/api/admin/products": {
			"get": {
				"operationId": "GetAllProducts",
				"responses": {
					"200": {
						"description": "Ok",
						"content": {
							"application/json": {
								"schema": {
									"anyOf": [
										{
											"$ref": "#/components/schemas/ApiResponse_ProductListResponse_"
										},
										{
											"$ref": "#/components/schemas/ApiErrorResponse"
										}
									]
								}
							}
						}
					}
				},
				"summary": "Get all products",
				"tags": [
					"Admin - Products"
				],
				"security": [
					{
						"bearerAuth": []
					}
				],
				"parameters": [
					{
						"in": "query",
						"name": "page",
						"required": false,
						"schema": {
							"default": 1,
							"format": "double",
							"type": "number"
						}
					},
					{
						"in": "query",
						"name": "limit",
						"required": false,
						"schema": {
							"default": 20,
							"format": "double",
							"type": "number"
						}
					}
				]
			},
			"post": {
				"operationId": "CreateProduct",
				"responses": {
					"200": {
						"description": "Ok",
						"content": {
							"application/json": {
								"schema": {
									"anyOf": [
										{
											"$ref": "#/components/schemas/ApiResponse_CreatedProductResponse_"
										},
										{
											"$ref": "#/components/schemas/ApiErrorResponse"
										}
									]
								}
							}
						}
					}
				},
				"summary": "Create a new product",
				"tags": [
					"Admin - Products"
				],
				"security": [
					{
						"bearerAuth": []
					}
				],
				"parameters": [],
				"requestBody": {
					"required": true,
					"content": {
						"application/json": {
							"schema": {
								"$ref": "#/components/schemas/CreateProductBody"
							}
						}
					}
				}
			},
			"put": {
				"operationId": "UpdateProduct",
				"responses": {
					"200": {
						"description": "Ok",
						"content": {
							"application/json": {
								"schema": {
									"anyOf": [
										{
											"$ref": "#/components/schemas/ApiMessageResponse"
										},
										{
											"$ref": "#/components/schemas/ApiErrorResponse"
										}
									]
								}
							}
						}
					}
				},
				"summary": "Update a product",
				"tags": [
					"Admin - Products"
				],
				"security": [
					{
						"bearerAuth": []
					}
				],
				"parameters": [
					{
						"in": "query",
						"name": "id",
						"required": true,
						"schema": {
							"format": "double",
							"type": "number"
						}
					}
				],
				"requestBody": {
					"required": true,
					"content": {
						"application/json": {
							"schema": {
								"$ref": "#/components/schemas/UpdateProductBody"
							}
						}
					}
				}
			},
			"delete": {
				"operationId": "DeleteProduct",
				"responses": {
					"200": {
						"description": "Ok",
						"content": {
							"application/json": {
								"schema": {
									"anyOf": [
										{
											"$ref": "#/components/schemas/ApiMessageResponse"
										},
										{
											"$ref": "#/components/schemas/ApiErrorResponse"
										}
									]
								}
							}
						}
					}
				},
				"summary": "Delete a product",
				"tags": [
					"Admin - Products"
				],
				"security": [
					{
						"bearerAuth": []
					}
				],
				"parameters": [
					{
						"in": "query",
						"name": "id",
						"required": true,
						"schema": {
							"format": "double",
							"type": "number"
						}
					}
				]
			}
		},
		"/api/admin/products/category": {
			"get": {
				"operationId": "GetProductsByCategory",
				"responses": {
					"200": {
						"description": "Ok",
						"content": {
							"application/json": {
								"schema": {
									"anyOf": [
										{
											"$ref": "#/components/schemas/ApiResponse_ProductResponse-Array_"
										},
										{
											"$ref": "#/components/schemas/ApiErrorResponse"
										}
									]
								}
							}
						}
					}
				},
				"summary": "Get products by category",
				"tags": [
					"Admin - Products"
				],
				"security": [
					{
						"bearerAuth": []
					}
				],
				"parameters": [
					{
						"in": "query",
						"name": "categoryId",
						"required": true,
						"schema": {
							"format": "double",
							"type": "number"
						}
					}
				]
			}
		},
		"/api/admin/products/{productId}": {
			"get": {
				"operationId": "GetProductById",
				"responses": {
					"200": {
						"description": "Ok",
						"content": {
							"application/json": {
								"schema": {
									"anyOf": [
										{
											"$ref": "#/components/schemas/ApiResponse_ProductResponse_"
										},
										{
											"$ref": "#/components/schemas/ApiErrorResponse"
										}
									]
								}
							}
						}
					}
				},
				"summary": "Get a product by ID",
				"tags": [
					"Admin - Products"
				],
				"security": [
					{
						"bearerAuth": []
					}
				],
				"parameters": [
					{
						"in": "path",
						"name": "productId",
						"required": true,
						"schema": {
							"format": "double",
							"type": "number"
						}
					}
				]
			}
		},
		"/api/admin/products/restore": {
			"put": {
				"operationId": "RestoreProduct",
				"responses": {
					"200": {
						"description": "Ok",
						"content": {
							"application/json": {
								"schema": {
									"anyOf": [
										{
											"$ref": "#/components/schemas/ApiMessageResponse"
										},
										{
											"$ref": "#/components/schemas/ApiErrorResponse"
										}
									]
								}
							}
						}
					}
				},
				"summary": "Restore a deleted product",
				"tags": [
					"Admin - Products"
				],
				"security": [
					{
						"bearerAuth": []
					}
				],
				"parameters": [
					{
						"in": "query",
						"name": "id",
						"required": true,
						"schema": {
							"format": "double",
							"type": "number"
						}
					}
				]
			}
		},
		"/api/admin/orders": {
			"get": {
				"operationId": "GetAllOrders",
				"responses": {
					"200": {
						"description": "Ok",
						"content": {
							"application/json": {
								"schema": {
									"anyOf": [
										{
											"$ref": "#/components/schemas/ApiResponse_OrderListResponse_"
										},
										{
											"$ref": "#/components/schemas/ApiErrorResponse"
										}
									]
								}
							}
						}
					}
				},
				"summary": "Get all orders",
				"tags": [
					"Admin - Orders"
				],
				"security": [
					{
						"bearerAuth": []
					}
				],
				"parameters": [
					{
						"in": "query",
						"name": "page",
						"required": false,
						"schema": {
							"default": 1,
							"format": "double",
							"type": "number"
						}
					},
					{
						"in": "query",
						"name": "limit",
						"required": false,
						"schema": {
							"default": 20,
							"format": "double",
							"type": "number"
						}
					}
				]
			},
			"post": {
				"operationId": "CreateOrder",
				"responses": {
					"200": {
						"description": "Ok",
						"content": {
							"application/json": {
								"schema": {
									"anyOf": [
										{
											"$ref": "#/components/schemas/ApiResponse_CreatedOrderResponse_"
										},
										{
											"$ref": "#/components/schemas/ApiErrorResponse"
										}
									]
								}
							}
						}
					}
				},
				"summary": "Create a new order",
				"tags": [
					"Admin - Orders"
				],
				"security": [
					{
						"bearerAuth": []
					}
				],
				"parameters": [],
				"requestBody": {
					"required": true,
					"content": {
						"application/json": {
							"schema": {
								"$ref": "#/components/schemas/CreateOrderBody"
							}
						}
					}
				}
			}
		},
		"/api/admin/orders/{orderId}": {
			"get": {
				"operationId": "GetOrderById",
				"responses": {
					"200": {
						"description": "Ok",
						"content": {
							"application/json": {
								"schema": {
									"anyOf": [
										{
											"$ref": "#/components/schemas/ApiResponse_OrderDetailResponse_"
										},
										{
											"$ref": "#/components/schemas/ApiErrorResponse"
										}
									]
								}
							}
						}
					}
				},
				"summary": "Get order detail by ID (includes items)",
				"tags": [
					"Admin - Orders"
				],
				"security": [
					{
						"bearerAuth": []
					}
				],
				"parameters": [
					{
						"in": "path",
						"name": "orderId",
						"required": true,
						"schema": {
							"format": "double",
							"type": "number"
						}
					}
				]
			}
		},
		"/api/admin/orders/status": {
			"put": {
				"operationId": "UpdateOrderStatus",
				"responses": {
					"200": {
						"description": "Ok",
						"content": {
							"application/json": {
								"schema": {
									"anyOf": [
										{
											"$ref": "#/components/schemas/ApiMessageResponse"
										},
										{
											"$ref": "#/components/schemas/ApiErrorResponse"
										}
									]
								}
							}
						}
					}
				},
				"summary": "Update order status",
				"tags": [
					"Admin - Orders"
				],
				"security": [
					{
						"bearerAuth": []
					}
				],
				"parameters": [
					{
						"in": "query",
						"name": "id",
						"required": true,
						"schema": {
							"format": "double",
							"type": "number"
						}
					}
				],
				"requestBody": {
					"required": true,
					"content": {
						"application/json": {
							"schema": {
								"$ref": "#/components/schemas/UpdateOrderStatusBody"
							}
						}
					}
				}
			}
		},
		"/api/admin/orders/cancel": {
			"put": {
				"operationId": "CancelOrder",
				"responses": {
					"200": {
						"description": "Ok",
						"content": {
							"application/json": {
								"schema": {
									"anyOf": [
										{
											"$ref": "#/components/schemas/ApiMessageResponse"
										},
										{
											"$ref": "#/components/schemas/ApiErrorResponse"
										}
									]
								}
							}
						}
					}
				},
				"summary": "Cancel an order",
				"tags": [
					"Admin - Orders"
				],
				"security": [
					{
						"bearerAuth": []
					}
				],
				"parameters": [
					{
						"in": "query",
						"name": "id",
						"required": true,
						"schema": {
							"format": "double",
							"type": "number"
						}
					}
				],
				"requestBody": {
					"required": true,
					"content": {
						"application/json": {
							"schema": {
								"$ref": "#/components/schemas/CancelOrderBody"
							}
						}
					}
				}
			}
		},
		"/api/client/profile": {
			"get": {
				"operationId": "GetProfile",
				"responses": {
					"200": {
						"description": "Ok",
						"content": {
							"application/json": {
								"schema": {
									"anyOf": [
										{
											"$ref": "#/components/schemas/ApiResponse_CustomerResponse_"
										},
										{
											"$ref": "#/components/schemas/ApiErrorResponse"
										}
									]
								}
							}
						}
					}
				},
				"summary": "Get my profile",
				"tags": [
					"Client - Profile"
				],
				"security": [
					{
						"bearerAuth": []
					}
				],
				"parameters": []
			},
			"put": {
				"operationId": "UpdateProfile",
				"responses": {
					"200": {
						"description": "Ok",
						"content": {
							"application/json": {
								"schema": {
									"anyOf": [
										{
											"$ref": "#/components/schemas/ApiMessageResponse"
										},
										{
											"$ref": "#/components/schemas/ApiErrorResponse"
										}
									]
								}
							}
						}
					}
				},
				"summary": "Update my profile",
				"tags": [
					"Client - Profile"
				],
				"security": [
					{
						"bearerAuth": []
					}
				],
				"parameters": [],
				"requestBody": {
					"required": true,
					"content": {
						"application/json": {
							"schema": {
								"$ref": "#/components/schemas/ClientUpdateProfileBody"
							}
						}
					}
				}
			}
		},
		"/api/client/change-password": {
			"put": {
				"operationId": "ChangePassword",
				"responses": {
					"200": {
						"description": "Ok",
						"content": {
							"application/json": {
								"schema": {
									"anyOf": [
										{
											"$ref": "#/components/schemas/ApiMessageResponse"
										},
										{
											"$ref": "#/components/schemas/ApiErrorResponse"
										}
									]
								}
							}
						}
					}
				},
				"summary": "Change my password",
				"tags": [
					"Client - Profile"
				],
				"security": [
					{
						"bearerAuth": []
					}
				],
				"parameters": [],
				"requestBody": {
					"required": true,
					"content": {
						"application/json": {
							"schema": {
								"$ref": "#/components/schemas/ClientChangePasswordBody"
							}
						}
					}
				}
			}
		},
		"/api/client/account": {
			"delete": {
				"operationId": "DeleteAccount",
				"responses": {
					"200": {
						"description": "Ok",
						"content": {
							"application/json": {
								"schema": {
									"anyOf": [
										{
											"$ref": "#/components/schemas/ApiMessageResponse"
										},
										{
											"$ref": "#/components/schemas/ApiErrorResponse"
										}
									]
								}
							}
						}
					}
				},
				"summary": "Delete my account",
				"tags": [
					"Client - Profile"
				],
				"security": [
					{
						"bearerAuth": []
					}
				],
				"parameters": []
			}
		},
		"/api/admin/customers": {
			"get": {
				"operationId": "GetAllCustomers",
				"responses": {
					"200": {
						"description": "Ok",
						"content": {
							"application/json": {
								"schema": {
									"anyOf": [
										{
											"$ref": "#/components/schemas/ApiResponse_CustomerListResponse_"
										},
										{
											"$ref": "#/components/schemas/ApiErrorResponse"
										}
									]
								}
							}
						}
					}
				},
				"summary": "Get all customers",
				"tags": [
					"Admin - Client"
				],
				"security": [
					{
						"bearerAuth": []
					}
				],
				"parameters": [
					{
						"in": "query",
						"name": "page",
						"required": false,
						"schema": {
							"default": 1,
							"format": "double",
							"type": "number"
						}
					},
					{
						"in": "query",
						"name": "limit",
						"required": false,
						"schema": {
							"default": 20,
							"format": "double",
							"type": "number"
						}
					}
				]
			},
			"post": {
				"operationId": "CreateCustomer",
				"responses": {
					"200": {
						"description": "Ok",
						"content": {
							"application/json": {
								"schema": {
									"anyOf": [
										{
											"$ref": "#/components/schemas/ApiResponse_CreatedIdResponse_"
										},
										{
											"$ref": "#/components/schemas/ApiErrorResponse"
										}
									]
								}
							}
						}
					}
				},
				"summary": "Create a new customer account",
				"tags": [
					"Admin - Client"
				],
				"security": [
					{
						"bearerAuth": []
					}
				],
				"parameters": [],
				"requestBody": {
					"required": true,
					"content": {
						"application/json": {
							"schema": {
								"$ref": "#/components/schemas/CreateCustomerBody"
							}
						}
					}
				}
			},
			"put": {
				"operationId": "UpdateCustomer",
				"responses": {
					"200": {
						"description": "Ok",
						"content": {
							"application/json": {
								"schema": {
									"anyOf": [
										{
											"$ref": "#/components/schemas/ApiMessageResponse"
										},
										{
											"$ref": "#/components/schemas/ApiErrorResponse"
										}
									]
								}
							}
						}
					}
				},
				"summary": "Update a customer",
				"tags": [
					"Admin - Client"
				],
				"security": [
					{
						"bearerAuth": []
					}
				],
				"parameters": [
					{
						"in": "query",
						"name": "id",
						"required": true,
						"schema": {
							"format": "double",
							"type": "number"
						}
					}
				],
				"requestBody": {
					"required": true,
					"content": {
						"application/json": {
							"schema": {
								"$ref": "#/components/schemas/UpdateCustomerBody"
							}
						}
					}
				}
			},
			"delete": {
				"operationId": "DeleteCustomer",
				"responses": {
					"200": {
						"description": "Ok",
						"content": {
							"application/json": {
								"schema": {
									"anyOf": [
										{
											"$ref": "#/components/schemas/ApiMessageResponse"
										},
										{
											"$ref": "#/components/schemas/ApiErrorResponse"
										}
									]
								}
							}
						}
					}
				},
				"summary": "Delete a customer",
				"tags": [
					"Admin - Client"
				],
				"security": [
					{
						"bearerAuth": []
					}
				],
				"parameters": [
					{
						"in": "query",
						"name": "id",
						"required": true,
						"schema": {
							"format": "double",
							"type": "number"
						}
					}
				]
			}
		},
		"/api/admin/customers/{customerId}": {
			"get": {
				"operationId": "GetCustomerById",
				"responses": {
					"200": {
						"description": "Ok",
						"content": {
							"application/json": {
								"schema": {
									"anyOf": [
										{
											"$ref": "#/components/schemas/ApiResponse_CustomerResponse_"
										},
										{
											"$ref": "#/components/schemas/ApiErrorResponse"
										}
									]
								}
							}
						}
					}
				},
				"summary": "Get a customer by ID",
				"tags": [
					"Admin - Client"
				],
				"security": [
					{
						"bearerAuth": []
					}
				],
				"parameters": [
					{
						"in": "path",
						"name": "customerId",
						"required": true,
						"schema": {
							"format": "double",
							"type": "number"
						}
					}
				]
			}
		},
		"/api/admin/customers/status": {
			"put": {
				"operationId": "UpdateStatus",
				"responses": {
					"200": {
						"description": "Ok",
						"content": {
							"application/json": {
								"schema": {
									"anyOf": [
										{
											"$ref": "#/components/schemas/ApiMessageResponse"
										},
										{
											"$ref": "#/components/schemas/ApiErrorResponse"
										}
									]
								}
							}
						}
					}
				},
				"summary": "Update customer status",
				"tags": [
					"Admin - Client"
				],
				"security": [
					{
						"bearerAuth": []
					}
				],
				"parameters": [
					{
						"in": "query",
						"name": "id",
						"required": true,
						"schema": {
							"format": "double",
							"type": "number"
						}
					}
				],
				"requestBody": {
					"required": true,
					"content": {
						"application/json": {
							"schema": {
								"$ref": "#/components/schemas/UpdateCustomerStatusBody"
							}
						}
					}
				}
			}
		},
		"/api/admin/customers/restore": {
			"put": {
				"operationId": "RestoreCustomer",
				"responses": {
					"200": {
						"description": "Ok",
						"content": {
							"application/json": {
								"schema": {
									"anyOf": [
										{
											"$ref": "#/components/schemas/ApiMessageResponse"
										},
										{
											"$ref": "#/components/schemas/ApiErrorResponse"
										}
									]
								}
							}
						}
					}
				},
				"summary": "Restore a deleted customer",
				"tags": [
					"Admin - Client"
				],
				"security": [
					{
						"bearerAuth": []
					}
				],
				"parameters": [
					{
						"in": "query",
						"name": "id",
						"required": true,
						"schema": {
							"format": "double",
							"type": "number"
						}
					}
				]
			}
		},
		"/api/admin/customers/reset-password": {
			"put": {
				"operationId": "ResetPassword",
				"responses": {
					"200": {
						"description": "Ok",
						"content": {
							"application/json": {
								"schema": {
									"anyOf": [
										{
											"$ref": "#/components/schemas/ApiMessageResponse"
										},
										{
											"$ref": "#/components/schemas/ApiErrorResponse"
										}
									]
								}
							}
						}
					}
				},
				"summary": "Reset a customer's password (admin only)",
				"tags": [
					"Admin - Client"
				],
				"security": [
					{
						"bearerAuth": []
					}
				],
				"parameters": [
					{
						"in": "query",
						"name": "id",
						"required": true,
						"schema": {
							"format": "double",
							"type": "number"
						}
					}
				],
				"requestBody": {
					"required": true,
					"content": {
						"application/json": {
							"schema": {
								"$ref": "#/components/schemas/AdminResetPasswordBody"
							}
						}
					}
				}
			}
		},
		"/api/admin/categories": {
			"get": {
				"operationId": "GetAllCategories",
				"responses": {
					"200": {
						"description": "Ok",
						"content": {
							"application/json": {
								"schema": {
									"anyOf": [
										{
											"$ref": "#/components/schemas/ApiResponse_CategoryListResponse_"
										},
										{
											"$ref": "#/components/schemas/ApiErrorResponse"
										}
									]
								}
							}
						}
					}
				},
				"summary": "Get all categories",
				"tags": [
					"Admin - Categories"
				],
				"security": [
					{
						"bearerAuth": []
					}
				],
				"parameters": [
					{
						"in": "query",
						"name": "page",
						"required": false,
						"schema": {
							"default": 1,
							"format": "double",
							"type": "number"
						}
					},
					{
						"in": "query",
						"name": "limit",
						"required": false,
						"schema": {
							"default": 20,
							"format": "double",
							"type": "number"
						}
					}
				]
			},
			"post": {
				"operationId": "CreateCategory",
				"responses": {
					"200": {
						"description": "Ok",
						"content": {
							"application/json": {
								"schema": {
									"anyOf": [
										{
											"$ref": "#/components/schemas/ApiResponse_CreatedCategoryResponse_"
										},
										{
											"$ref": "#/components/schemas/ApiErrorResponse"
										}
									]
								}
							}
						}
					}
				},
				"summary": "Create a new category",
				"tags": [
					"Admin - Categories"
				],
				"security": [
					{
						"bearerAuth": []
					}
				],
				"parameters": [],
				"requestBody": {
					"required": true,
					"content": {
						"application/json": {
							"schema": {
								"$ref": "#/components/schemas/CreateCategoryBody"
							}
						}
					}
				}
			},
			"put": {
				"operationId": "UpdateCategory",
				"responses": {
					"200": {
						"description": "Ok",
						"content": {
							"application/json": {
								"schema": {
									"anyOf": [
										{
											"$ref": "#/components/schemas/ApiMessageResponse"
										},
										{
											"$ref": "#/components/schemas/ApiErrorResponse"
										}
									]
								}
							}
						}
					}
				},
				"summary": "Update a category",
				"tags": [
					"Admin - Categories"
				],
				"security": [
					{
						"bearerAuth": []
					}
				],
				"parameters": [
					{
						"in": "query",
						"name": "id",
						"required": true,
						"schema": {
							"format": "double",
							"type": "number"
						}
					}
				],
				"requestBody": {
					"required": true,
					"content": {
						"application/json": {
							"schema": {
								"$ref": "#/components/schemas/UpdateCategoryBody"
							}
						}
					}
				}
			},
			"delete": {
				"operationId": "DeleteCategory",
				"responses": {
					"200": {
						"description": "Ok",
						"content": {
							"application/json": {
								"schema": {
									"anyOf": [
										{
											"$ref": "#/components/schemas/ApiMessageResponse"
										},
										{
											"$ref": "#/components/schemas/ApiErrorResponse"
										}
									]
								}
							}
						}
					}
				},
				"summary": "Delete a category",
				"tags": [
					"Admin - Categories"
				],
				"security": [
					{
						"bearerAuth": []
					}
				],
				"parameters": [
					{
						"in": "query",
						"name": "id",
						"required": true,
						"schema": {
							"format": "double",
							"type": "number"
						}
					}
				]
			}
		},
		"/api/admin/categories/{categoryId}": {
			"get": {
				"operationId": "GetCategoryById",
				"responses": {
					"200": {
						"description": "Ok",
						"content": {
							"application/json": {
								"schema": {
									"anyOf": [
										{
											"$ref": "#/components/schemas/ApiResponse_CategoryResponse_"
										},
										{
											"$ref": "#/components/schemas/ApiErrorResponse"
										}
									]
								}
							}
						}
					}
				},
				"summary": "Get a category by ID",
				"tags": [
					"Admin - Categories"
				],
				"security": [
					{
						"bearerAuth": []
					}
				],
				"parameters": [
					{
						"in": "path",
						"name": "categoryId",
						"required": true,
						"schema": {
							"format": "double",
							"type": "number"
						}
					}
				]
			}
		},
		"/api/admin/categories/restore": {
			"put": {
				"operationId": "RestoreCategory",
				"responses": {
					"200": {
						"description": "Ok",
						"content": {
							"application/json": {
								"schema": {
									"anyOf": [
										{
											"$ref": "#/components/schemas/ApiMessageResponse"
										},
										{
											"$ref": "#/components/schemas/ApiErrorResponse"
										}
									]
								}
							}
						}
					}
				},
				"summary": "Restore a deleted category",
				"tags": [
					"Admin - Categories"
				],
				"security": [
					{
						"bearerAuth": []
					}
				],
				"parameters": [
					{
						"in": "query",
						"name": "id",
						"required": true,
						"schema": {
							"format": "double",
							"type": "number"
						}
					}
				]
			}
		},
		"/api/auth/login": {
			"post": {
				"operationId": "Login",
				"responses": {
					"200": {
						"description": "Ok",
						"content": {
							"application/json": {
								"schema": {
									"anyOf": [
										{
											"$ref": "#/components/schemas/ApiResponse_StaffLoginResponse_"
										},
										{
											"$ref": "#/components/schemas/ApiErrorResponse"
										}
									]
								}
							}
						}
					}
				},
				"summary": "Staff login",
				"tags": [
					"Auth - Login & Logout"
				],
				"security": [],
				"parameters": [],
				"requestBody": {
					"required": true,
					"content": {
						"application/json": {
							"schema": {
								"$ref": "#/components/schemas/LoginBody"
							}
						}
					}
				}
			}
		},
		"/api/auth/client/login": {
			"post": {
				"operationId": "LoginCustomer",
				"responses": {
					"200": {
						"description": "Ok",
						"content": {
							"application/json": {
								"schema": {
									"anyOf": [
										{
											"$ref": "#/components/schemas/ApiResponse_CustomerLoginResponse_"
										},
										{
											"$ref": "#/components/schemas/ApiErrorResponse"
										}
									]
								}
							}
						}
					}
				},
				"summary": "Customer login",
				"tags": [
					"Auth - Login & Logout"
				],
				"security": [],
				"parameters": [],
				"requestBody": {
					"required": true,
					"content": {
						"application/json": {
							"schema": {
								"$ref": "#/components/schemas/LoginBody"
							}
						}
					}
				}
			}
		},
		"/api/auth/logout": {
			"post": {
				"operationId": "Logout",
				"responses": {
					"200": {
						"description": "Ok",
						"content": {
							"application/json": {
								"schema": {
									"anyOf": [
										{
											"$ref": "#/components/schemas/ApiMessageResponse"
										},
										{
											"$ref": "#/components/schemas/ApiErrorResponse"
										}
									]
								}
							}
						}
					}
				},
				"summary": "Logout authenticated user",
				"tags": [
					"Auth - Login & Logout"
				],
				"security": [
					{
						"bearerAuth": []
					}
				],
				"parameters": []
			}
		}
	},
	"servers": [
		{
			"url": "/"
		}
	]
}